{
    "grit": "<:G_:881974742326857828> <:R_:881975539169120267> <:I_:881975861333606440> <:10:881976704069926943>",
    "big_oof": ":b: <:I_:881975861333606440> <:G_:881974742326857828>   <:oof:879551416056836106>",
    "succ": "<:sss:882271624294989834> <:uuu:882671601005494303> <:ccc:882670792582762506> <:ccc:882670792582762506> <:funnyrelatable2:879479344022569000>",
    "jawn": ":regional_indicator_j: :a: :regional_indicator_w: :regional_indicator_n:",
    "sf": ":a: :regional_indicator_l: :regional_indicator_l:   :m: :regional_indicator_y:   <:hhh:882271553939722281> :o: :m: <:I_:881975861333606440> :regional_indicator_e: <:sss:882271624294989834>   :regional_indicator_l: :o: :regional_indicator_v: :regional_indicator_e:   <:sss:882271624294989834> :a: :regional_indicator_l: :regional_indicator_e: <:sss:882271624294989834> :regional_indicator_f: :o: <:R_:881975539169120267> <:ccc:882670792582762506> :regional_indicator_e:",
    "homies": "<:kissing_the_homies:880446604312731748>",
    "emjoi": ":heart_exclamation: :regional_indicator_e: :regional_indicator_m: <:j_:887091168628854804> :o2: <:I_:881975861333606440>",
    "cuss": "<:ccc:882670792582762506> <:uuu:882671601005494303> <:sss:882271624294989834> <:sss:882271624294989834>",
    "dude": "<:gritty:881974805333680229>",
    "pog": "<:cursedpog:882668904281960478>",
    "ez": ":regional_indicator_e: :zzz:",
    "ahhh": ":sob::mega::regional_indicator_a: :regional_indicator_a: :regional_indicator_a: :regional_indicator_a: :regional_indicator_a: :regional_indicator_a: :regional_indicator_a: :regional_indicator_a: :regional_indicator_a: :regional_indicator_a: :regional_indicator_a: :regional_indicator_a: :regional_indicator_a: :regional_indicator_a:"
}